{"title":"YES24 티켓 ─ 엔젤티켓","url":"http://ticket.yes24.com/Pages/Events/HotEvent/PromotionInfo.aspx?id=2577","favicon":"http://tkfile.yes24.com/img/icon.png","elements":[{"title":"뮤지컬 〈라흐마니노프〉","contents":"<td class=\"grade\">\t\t\t\t\t\t\t\t\t<em class=\"bl_rnd\">&nbsp;</em>R석\t\t\t\t\t\t\t\t</td>\t\t\t\t\t\t\t\t<td class=\"price\">\t\t\t\t\t\t\t\t\t77,000원\t\t\t\t\t\t\t\t</td>\t\t\t\t\t\t\t\t<td class=\"dc_price\">\t\t\t\t\t\t\t\t\t<em>→</em>51,500원\t\t\t\t\t\t\t\t</td>","link":"http://ticket.yes24.com/Perf/45040","retrieved":1680488933962,"image":"http://tkfile.yes24.com/upload2/perfblog/202304/20230403/20230403-45040.jpg"}]}