{"title":"YES24 티켓 ─ 엔젤티켓 모바일","url":"http://m.ticket.yes24.com/Discount/Angel.aspx","favicon":"http://m.ticket.yes24.com/Discount/favicon.ico","elements":[{"title":"뮤지컬 <쓰릴 미>","contents":"<p class=\"goods_name\">뮤지컬 &lt;쓰릴 미&gt;</p><p class=\"goods_price\"><span class=\"txt_sale yes_b\"><em class=\"yes_b\">30</em>%<em class=\"blind\">할인</em></span><span class=\"txt_num\">\n\t\t\t\t\t\t\t\t\t\t\t\t\t\t\t\t\t\t\t<strong class=\"priceO\"><em class=\"blind\">정가</em> <em class=\"yes_b\">44,000원</em></strong>\n\t\t\t\t\t\t\t\t\t\t\t\t\t\t\t\t\t\t\t<strong class=\"priceS\"><em class=\"blind\">할인가</em> <em class=\"yes_b\">28,400원</em></strong>\n\t\t\t\t\t\t\t\t\t\t\t\t\t\t\t\t\t\t  </span></p><div class=\"goods_benefit\">장당 2,400원 YES포인트 적립</div><div class=\"goods_cmt\">7/19 ~ 7/31 공연(일부회차 제외)</div>","link":"http://m.ticket.yes24.com/Perf/42439","retrieved":1658108813816,"image":"http://tkfile.yes24.com/upload2/perfblog/202207/20220718/20220718-42439.jpg"},{"title":"뮤지컬 <말리의 어제보다 특별한 오늘>","contents":"<p class=\"goods_name\">뮤지컬 &lt;말리의 어제보다 특별한 오늘&gt;</p><p class=\"goods_price\"><span class=\"txt_sale yes_b\"><em class=\"yes_b\">40</em>%<em class=\"blind\">할인</em></span><span class=\"txt_num\">\n\t\t\t\t\t\t\t\t\t\t\t\t\t\t\t\t\t\t\t<strong class=\"priceO\"><em class=\"blind\">정가</em> <em class=\"yes_b\">50,000원</em></strong>\n\t\t\t\t\t\t\t\t\t\t\t\t\t\t\t\t\t\t\t<strong class=\"priceS\"><em class=\"blind\">할인가</em> <em class=\"yes_b\">27,600원</em></strong>\n\t\t\t\t\t\t\t\t\t\t\t\t\t\t\t\t\t\t  </span></p><div class=\"goods_benefit\">장당 2,400원 YES포인트 적립</div><div class=\"goods_cmt\">7/18 ~ 7/29</div>","link":"http://m.ticket.yes24.com/Perf/42549","retrieved":1658108813818,"image":"http://tkfile.yes24.com/upload2/perfblog/202207/20220718/20220718-42549.jpg"},{"title":"연극 <한성의 이발사>","contents":"<p class=\"goods_name\">연극 &lt;한성의 이발사&gt;</p><p class=\"goods_price\"><span class=\"txt_sale yes_b\"><em class=\"yes_b\">40</em>%<em class=\"blind\">할인</em></span><span class=\"txt_num\">\n\t\t\t\t\t\t\t\t\t\t\t\t\t\t\t\t\t\t\t<strong class=\"priceO\"><em class=\"blind\">정가</em> <em class=\"yes_b\">33,000원</em></strong>\n\t\t\t\t\t\t\t\t\t\t\t\t\t\t\t\t\t\t\t<strong class=\"priceS\"><em class=\"blind\">할인가</em> <em class=\"yes_b\">17,400원</em></strong>\n\t\t\t\t\t\t\t\t\t\t\t\t\t\t\t\t\t\t  </span></p><div class=\"goods_benefit\">장당 2,400원 YES포인트 적립</div>","link":"http://m.ticket.yes24.com/Perf/42731","retrieved":1658108813821,"image":"http://tkfile.yes24.com/upload2/perfblog/202207/20220718/20220718-42731_1.jpg"},{"title":"연극 <자연빵> - 싱크넥스트22","contents":"<p class=\"goods_name\">연극 &lt;자연빵&gt; - 싱크넥스트22</p><p class=\"goods_price\"><span class=\"txt_sale yes_b\"><em class=\"yes_b\">50</em>%<em class=\"blind\">할인</em></span><span class=\"txt_num\">\n\t\t\t\t\t\t\t\t\t\t\t\t\t\t\t\t\t\t\t<strong class=\"priceO\"><em class=\"blind\">정가</em> <em class=\"yes_b\">50,000원</em></strong>\n\t\t\t\t\t\t\t\t\t\t\t\t\t\t\t\t\t\t\t<strong class=\"priceS\"><em class=\"blind\">할인가</em> <em class=\"yes_b\">22,600원</em></strong>\n\t\t\t\t\t\t\t\t\t\t\t\t\t\t\t\t\t\t  </span></p><div class=\"goods_benefit\">장당 2,400원 YES포인트 적립</div><div class=\"goods_cmt\">8/4 ~ 8/7 공연(일부회차 제외)</div>","link":"http://m.ticket.yes24.com/Perf/42122","retrieved":1658108813822,"image":"http://tkfile.yes24.com/upload2/perfblog/202207/20220718/20220718-42122.jpg"}]}