{"title":"예스24 티켓","url":"http://ticket.yes24.com/New/Notice/NoticeMain.aspx","favicon":"http://tkfile.yes24.com/img/icon.png","elements":[{"title":"[부산] 2025 라이브가족뮤지컬 [알라딘] 티켓오픈 안내","contents":"2025.02.18(화) 09:00","link":"http://ticket.yes24.com/New/Notice/NoticeMain.aspx#id=15619","retrieved":1739503249313},{"title":"Have A Nice Day #11 티켓 오픈 안내","contents":"2025.02.19(수) 18:00","link":"http://ticket.yes24.com/New/Notice/NoticeMain.aspx#id=15618","retrieved":1739438317359},{"title":"단독판매SHADOW: A New Musical- The Beginning / 창작뮤지컬 [쉐도우:더 비기닝] 티켓오픈 안내","contents":"2025.02.19(수) 14:00","link":"http://ticket.yes24.com/New/Notice/NoticeMain.aspx#id=15617","retrieved":1739434938233},{"title":"[부산] 뮤지컬 [돈 주앙] 프렌치 오리지널 내한공연 티켓오픈 안내","contents":"2025.02.18(화) 14:00","link":"http://ticket.yes24.com/New/Notice/NoticeMain.aspx#id=15615","retrieved":1739423817209},{"title":"단독판매2025 KIM MYUNGSOO BIRTHDAY PARTY 'Every day, L+ovely day' SEASON 2 티켓오픈 안내","contents":"2025.02.17(월) 19:00<a class=\"noti-btn-pop\" presaletit1=\"팬클럽 선예매\" presaletit2=\"\" presaletime1=\"2025.02.14(금) 19:00\" presaletime2=\"\"><img src=\"http://tkfile.yes24.com/imgNew/common/btn-notice1.png\" alt=\"\"></a>","link":"http://ticket.yes24.com/New/Notice/NoticeMain.aspx#id=15614","retrieved":1739414870286},{"title":"시스템 점검으로 인한 서비스 일시 중지 안내(2/16)","contents":"","link":"http://ticket.yes24.com/New/Notice/NoticeMain.aspx#id=15613","retrieved":1739409479609},{"title":"[수원] 2025 라이브 가족뮤지컬 [아기돼지삼형제] 티켓오픈 안내","contents":"2025.02.17(월) 09:00","link":"http://ticket.yes24.com/New/Notice/NoticeMain.aspx#id=15612","retrieved":1739409479615},{"title":"단독판매DAY6 3RD WORLD TOUR〈FOREVER YOUNG〉in DAEGU 좌석배치도 변경안내","contents":"2025.02.14(금) 20:00<a class=\"noti-btn-pop\" presaletit1=\"팬클럽 선예매\" presaletit2=\"\" presaletime1=\"2025.02.13(목) 20:00\" presaletime2=\"\"><img src=\"http://tkfile.yes24.com/imgNew/common/btn-notice1.png\" alt=\"\"></a>","link":"http://ticket.yes24.com/New/Notice/NoticeMain.aspx#id=15611","retrieved":1739409479615},{"title":"[청주] 2025 앤서니브라운 가족뮤지컬 [우리아빠가최고야] 티켓오픈 안내","contents":"2025.02.17(월) 09:00","link":"http://ticket.yes24.com/New/Notice/NoticeMain.aspx#id=15610","retrieved":1739409479615},{"title":"Flight to Denmark Again! (서울) 티켓 오픈 안내","contents":"2025.02.14(금) 10:00","link":"http://ticket.yes24.com/New/Notice/NoticeMain.aspx#id=15609","retrieved":1739337472669},{"title":"단독판매2025 그린캠프페스티벌 블라인드티켓 오픈 안내","contents":"2025.02.17(월) 13:00","link":"http://ticket.yes24.com/New/Notice/NoticeMain.aspx#id=15608","retrieved":1739337472674},{"title":"[안양] 2025 연극 [친정엄마와 2박3일] 티켓오픈 안내","contents":"2025.02.17(월) 14:00","link":"http://ticket.yes24.com/New/Notice/NoticeMain.aspx#id=15607","retrieved":1739328397198},{"title":"단독판매Tatsuya Kitani Asia Tour 2025 티켓오픈 안내","contents":"2025.02.21(금) 20:00","link":"http://ticket.yes24.com/New/Notice/NoticeMain.aspx#id=15606","retrieved":1739330437539},{"title":"20집 발매 기념 조용필＆위대한탄생 Concert - 대전 티켓오픈 안내","contents":"2025.02.19(수) 14:00","link":"http://ticket.yes24.com/New/Notice/NoticeMain.aspx#id=15605","retrieved":1739337472675},{"title":"[대구] 2025 라이브가족뮤지컬 [정글북] 티켓오픈 안내","contents":"2025.02.13(목) 09:00","link":"http://ticket.yes24.com/New/Notice/NoticeMain.aspx#id=15604","retrieved":1739255055463},{"title":"[부산] 뮤지컬 [웃는 남자] 티켓오픈 안내","contents":"2025.02.14(금) 15:00","link":"http://ticket.yes24.com/New/Notice/NoticeMain.aspx#id=15603","retrieved":1739251043788},{"title":"[대구] 뮤지컬 [웃는 남자] 티켓오픈 안내","contents":"2025.02.14(금) 14:00","link":"http://ticket.yes24.com/New/Notice/NoticeMain.aspx#id=15602","retrieved":1739251043798},{"title":"2024-25 이은미 라이브 투어 [MOVE ON]-대구공연 티켓오픈 안내","contents":"2025.02.14(금) 16:00","link":"http://ticket.yes24.com/New/Notice/NoticeMain.aspx#id=15601","retrieved":1739251043799},{"title":"2024-25 이은미 라이브 투어 [MOVE ON]-안산공연 티켓오픈 안내","contents":"2025.02.14(금) 15:00","link":"http://ticket.yes24.com/New/Notice/NoticeMain.aspx#id=15600","retrieved":1739251043802},{"title":"뮤지컬〈돈 주앙〉프렌치 오리지널 내한공연 티켓오픈안내","contents":"2025.02.19(수) 15:00","link":"http://ticket.yes24.com/New/Notice/NoticeMain.aspx#id=15599","retrieved":1739244063524}]}