{"title":"예스24 티켓 모바일","url":"http://m.ticket.yes24.com/Notice/List.aspx?type=1","favicon":"http://tkfile.yes24.com/img/mobile/icon/icon.png","elements":[{"title":"[안산] 2023 변진섭 전국투어 콘서트：변천사 티켓 오픈 안내","contents":"2023-09-20(수) 16:00","link":"http://m.ticket.yes24.com/Notice/Detail.aspx?bid=13525&order=1","retrieved":1695097100081},{"title":"[안산] 2023 이은미 전국투어 콘서트 [NOCTURN] 티켓 오픈 안내","contents":"2023-09-20(수) 14:00","link":"http://m.ticket.yes24.com/Notice/Detail.aspx?bid=13523&order=1","retrieved":1695097100084},{"title":"[서울] 2023 에일리 전국투어 ‘I AM：COLORFUL’ 티켓 오픈 안내","contents":"2023-09-22(금) 14:00","link":"http://m.ticket.yes24.com/Notice/Detail.aspx?bid=13521&order=1","retrieved":1695090124313},{"title":"YESUNG SOLO CONCERT - Unfading Sense 티켓오픈안내","contents":"2023-10-06(금) 20:00","link":"http://m.ticket.yes24.com/Notice/Detail.aspx?bid=13520&order=1","retrieved":1695097100096},{"title":"Ivan Usovich：Solo Standup Comedy Concert (RUS) 티켓 오픈 안내","contents":"2023-09-20(수) 12:00","link":"http://m.ticket.yes24.com/Notice/Detail.aspx?bid=13519&order=1","retrieved":1695085217164},{"title":"≪해리 포터와 불의 잔™ 인 콘서트≫ 발코니석 티켓 오픈 안내","contents":"2023-09-19(화) 14:00","link":"http://m.ticket.yes24.com/Notice/Detail.aspx?bid=13518&order=1","retrieved":1695025127146},{"title":"[대구] 2023 백지영 전국투어 콘서트 〈BAEK SPACE〉 티켓 오픈 안내","contents":"2023-09-21(목) 16:00","link":"http://m.ticket.yes24.com/Notice/Detail.aspx?bid=13517&order=1","retrieved":1695025127147},{"title":"[광주] 2023 에일리 전국투어 ‘I AM：COLORFUL’ 공연장, 오픈일 변경 안내","contents":"2023-09-22(금) 19:00","link":"http://m.ticket.yes24.com/Notice/Detail.aspx?bid=13516&order=1","retrieved":1695021211234},{"title":"2023 TWICE FANMEETING 〈ONCE AGAIN〉 티켓오픈안내","contents":"2023-09-25(월) 20:00","link":"http://m.ticket.yes24.com/Notice/Detail.aspx?bid=13515&order=1","retrieved":1695028525057},{"title":"2023 THE CRY ground 티켓 오픈 안내","contents":"2023-09-18(월) 18:00","link":"http://m.ticket.yes24.com/Notice/Detail.aspx?bid=13514&order=1","retrieved":1695014061200}]}