{"title":"예스24 티켓 모바일","url":"http://m.ticket.yes24.com/Notice/List.aspx?type=1","favicon":"http://tkfile.yes24.com/img/mobile/icon/icon.png","elements":[{"title":"Xdinary Heroes〈Beautiful Mind〉World Tour in SEOUL 티켓오픈안내","contents":"2025-04-01(화) 20:00","link":"http://m.ticket.yes24.com/Notice/Detail.aspx?bid=15779&order=1","retrieved":1742199938394},{"title":"콘서트 가이드 김성민과 함께하는 [영도에서 떠나는 예술여행 ‘르네상스’] - 부산 티켓오픈안내","contents":"2025-03-21(금) 14:00","link":"http://m.ticket.yes24.com/Notice/Detail.aspx?bid=15778&order=1","retrieved":1742199938395},{"title":"[부산] 튠에이드 [하나되는 너와 나의 목소리, 아카펠라!] 티켓 오픈 안내","contents":"2025-03-18(화) 14:00","link":"http://m.ticket.yes24.com/Notice/Detail.aspx?bid=15777&order=1","retrieved":1742192843361},{"title":"디즈니 & 픽사 OST 콘서트 티켓오픈 안내입니다.","contents":"2025-03-18(화) 11:00","link":"http://m.ticket.yes24.com/Notice/Detail.aspx?bid=15776&order=1","retrieved":1742192843361},{"title":"쇼뮤지컬 어게인 [드림하이] (Showmusical Again [DreamHigh]) 2차 티켓오픈 안내","contents":"2025-03-24(월) 16:00","link":"http://m.ticket.yes24.com/Notice/Detail.aspx?bid=15775&order=1","retrieved":1742195937258},{"title":"〈2025 롯데콘서트홀 마티네 〈황수미의 사운드트랙〉〉 티켓오픈 안내","contents":"2025-03-19(수) 14:00","link":"http://m.ticket.yes24.com/Notice/Detail.aspx?bid=15774&order=1","retrieved":1742188726811},{"title":"[광주] 2025 김창옥 토크콘서트 시즌5 티켓 오픈 안내","contents":"2025-03-19(수) 10:00","link":"http://m.ticket.yes24.com/Notice/Detail.aspx?bid=15773&order=1","retrieved":1742188726812},{"title":"Live on Spring in 대구(라이브 온 스프링 인 대구) N.Flying (엔플라잉), Band Nah (나상현씨밴드) 티켓 오픈 안내","contents":"2025-03-21(금) 20:00","link":"http://m.ticket.yes24.com/Notice/Detail.aspx?bid=15772&order=1","retrieved":1742188726813},{"title":"Live on Spring in 대구(라이브 온 스프링 인 대구) 홍이삭(Isaac Hong), 리도어(Redoor) 티켓 오픈 안내","contents":"2025-03-20(목) 20:00","link":"http://m.ticket.yes24.com/Notice/Detail.aspx?bid=15771&order=1","retrieved":1742188726815},{"title":"[청주] 2025 라이브가족뮤지컬 [인어공주] 티켓오픈 안내","contents":"2025-03-20(목) 10:00","link":"http://m.ticket.yes24.com/Notice/Detail.aspx?bid=15769&order=1","retrieved":1742182449654}]}