{"title":"예스24 티켓 모바일","url":"http://m.ticket.yes24.com/Notice/List.aspx?type=1","favicon":"http://tkfile.yes24.com/img/mobile/icon/icon.png","elements":[{"title":"뮤지컬 [더데빌:파우스트] 2024 새해, 3차 티켓 오픈 안내","contents":"2023-12-12(화) 11:00","link":"http://m.ticket.yes24.com/Notice/Detail.aspx?bid=13817&order=1","retrieved":1701839622067},{"title":"[구미] 뽀로로 20주년 스페셜 매직 싱어롱쇼 [슈퍼스타 뽀로로 드림콘서트] 시즌 2 티켓오픈 안내","contents":"2023-12-08(금) 11:00","link":"http://m.ticket.yes24.com/Notice/Detail.aspx?bid=13816&order=1","retrieved":1701836236038},{"title":"뮤지컬 [은하철도의 밤] 2차 티켓 오픈 안내","contents":"2023-12-12(화) 11:00","link":"http://m.ticket.yes24.com/Notice/Detail.aspx?bid=13815&order=1","retrieved":1701753207672},{"title":"[양산] 뽀로로 20주년 스페셜 매직 싱어롱쇼 [슈퍼스타 뽀로로 드림콘서트] 시즌 2 티켓오픈 안내","contents":"2023-12-07(목) 10:00","link":"http://m.ticket.yes24.com/Notice/Detail.aspx?bid=13814&order=1","retrieved":1701749806862},{"title":"Macaroni Empitsu 내한공연 티켓 오픈 안내","contents":"2023-12-08(금) 12:00","link":"http://m.ticket.yes24.com/Notice/Detail.aspx?bid=13813&order=1","retrieved":1701738204003},{"title":"화가시리즈 - 뮤지컬 〈에곤 실레〉 3차 티켓오픈 안내","contents":"2023-12-08(금) 15:00","link":"http://m.ticket.yes24.com/Notice/Detail.aspx?bid=13812&order=1","retrieved":1701684980514},{"title":"화가시리즈 - 뮤지컬 〈모딜리아니〉 3차 티켓오픈 안내","contents":"2023-12-07(목) 03:00","link":"http://m.ticket.yes24.com/Notice/Detail.aspx?bid=13811&order=1","retrieved":1701684980516},{"title":"[수원] 2024 김창옥 토크콘서트 시즌3 티켓 오픈 안내","contents":"2023-12-07(목) 14:00","link":"http://m.ticket.yes24.com/Notice/Detail.aspx?bid=13809&order=1","retrieved":1701677912198},{"title":"[남양주] 2024 장윤정 라이브 콘서트 티켓 오픈 안내","contents":"2023-12-08(금) 16:00","link":"http://m.ticket.yes24.com/Notice/Detail.aspx?bid=13808&order=1","retrieved":1701674039528},{"title":"[천안] 가족뮤지컬 [꼬마버스 타요 - 용감한 구조대 레스큐 타요] 티켓오픈 안내","contents":"2023-12-06(수) 10:00","link":"http://m.ticket.yes24.com/Notice/Detail.aspx?bid=13807&order=1","retrieved":1701663414450}]}