{"title":"예스24 티켓 모바일","url":"http://m.ticket.yes24.com/Notice/List.aspx?type=1","favicon":"http://tkfile.yes24.com/img/mobile/icon/icon.png","elements":[{"title":"90’s 전설이 부르다 6탄 - 대환장 나이트 페스티벌 티켓 오픈 안내","contents":"2023-11-02(목) 15:00","link":"http://m.ticket.yes24.com/Notice/Detail.aspx?bid=13680&order=1","retrieved":1698642848826},{"title":"폴리팝(두들팝ver.2) 1차 티켓오픈 안내","contents":"2023-11-02(목) 11:00","link":"http://m.ticket.yes24.com/Notice/Detail.aspx?bid=13679&order=1","retrieved":1698635677723},{"title":"[대구] 신구쇼 - 니들이 트롯을 알아? 티켓 오픈 안내","contents":"2023-10-30(월) 15:00","link":"http://m.ticket.yes24.com/Notice/Detail.aspx?bid=13678&order=1","retrieved":1698387541661},{"title":"Loossemble 1st FAN-CON [Make a voyage] Online Live Streaming 티켓 오픈 안내","contents":"2023-11-03(금) 20:00","link":"http://m.ticket.yes24.com/Notice/Detail.aspx?bid=13677&order=1","retrieved":1698383622837},{"title":"Loossemble 1st FAN-CON [Make a voyage] 티켓 오픈 안내","contents":"2023-11-03(금) 20:00","link":"http://m.ticket.yes24.com/Notice/Detail.aspx?bid=13676&order=1","retrieved":1698383622840},{"title":"[일산] 나훈아 연말 콘서트 12月에 IN DECEMBER 티켓 오픈 안내","contents":"2023-10-31(화) 10:00","link":"http://m.ticket.yes24.com/Notice/Detail.aspx?bid=13675&order=1","retrieved":1698376454956},{"title":"다니엘 시저 (Daniel Caesar) 내한공연 티켓 오픈 안내","contents":"2023-10-31(화) 12:00","link":"http://m.ticket.yes24.com/Notice/Detail.aspx?bid=13674&order=1","retrieved":1698376454959},{"title":"THE BOYZ 2ND WORLD TOUR : ZENERATION - ENCORE 티켓오픈 안내","contents":"2023-11-02(목) 20:00","link":"http://m.ticket.yes24.com/Notice/Detail.aspx?bid=13673&order=1","retrieved":1698376454965},{"title":"〈빅보스랜드 - 빅파이브 콘서트〉 티켓 오픈 안내","contents":"2023-10-31(화) 16:00","link":"http://m.ticket.yes24.com/Notice/Detail.aspx?bid=13672&order=1","retrieved":1698373208214},{"title":"가족뮤지컬 〈장화 신은 고양이 비긴즈〉 플레이버전 2차 티켓 오픈 안내","contents":"2023-10-31(화) 11:00","link":"http://m.ticket.yes24.com/Notice/Detail.aspx?bid=13671&order=1","retrieved":1698326217496}]}