{"title":"예스24 티켓 모바일","url":"http://m.ticket.yes24.com/Notice/List.aspx?type=1","favicon":"http://tkfile.yes24.com/img/mobile/icon/icon.png","elements":[{"title":"2025 LOVESOME - 반 고흐, 영혼의 편지 양일권 티켓 오픈 안내","contents":"2025-04-04(금) 14:00","link":"http://m.ticket.yes24.com/Notice/Detail.aspx?bid=15845&order=1","retrieved":1743484749345},{"title":"뮤지컬 [랭보] 앵콜 마지막 티켓오픈 안내","contents":"2025-04-08(화) 14:00","link":"http://m.ticket.yes24.com/Notice/Detail.aspx?bid=15844&order=1","retrieved":1743484749345},{"title":"The Magic, 조수미 & 위너스 - 전주 티켓오픈안내","contents":"2025-04-04(금) 14:00","link":"http://m.ticket.yes24.com/Notice/Detail.aspx?bid=15842&order=1","retrieved":1743484749348},{"title":"뮤지컬 <알라딘> 마지막 티켓오픈 안내","contents":"2025-04-10(목) 14:00","link":"http://m.ticket.yes24.com/Notice/Detail.aspx?bid=15841&order=1","retrieved":1743477151336},{"title":"[대구] 2025 라이브가족뮤지컬〈백설공주〉 티켓오픈 안내","contents":"2025-04-03(목) 10:00","link":"http://m.ticket.yes24.com/Notice/Detail.aspx?bid=15840&order=1","retrieved":1743471703974},{"title":"DAY6 3RD WORLD TOUR〈FOREVER YOUNG〉FINALE in SEOUL 티켓오픈안내","contents":"2025-04-14(월) 20:00","link":"http://m.ticket.yes24.com/Notice/Detail.aspx?bid=15839&order=1","retrieved":1743409594224},{"title":"노엘(NO:EL) 단독 콘서트 〈No.1 : El Arte〉 티켓 오픈 안내","contents":"2025-04-17(목) 18:00","link":"http://m.ticket.yes24.com/Notice/Detail.aspx?bid=15838&order=1","retrieved":1743412877426},{"title":"가족오페라 [신콩쥐] - 부산 티켓오픈안내","contents":"2025-04-03(목) 14:00","link":"http://m.ticket.yes24.com/Notice/Detail.aspx?bid=15837&order=1","retrieved":1743394970675},{"title":"아디오스 피아졸라, 라이브 탱고 - 서울 티켓오픈 안내입니다.","contents":"2025-04-03(목) 14:00","link":"http://m.ticket.yes24.com/Notice/Detail.aspx?bid=15836&order=1","retrieved":1743394970677},{"title":"[서울바앤스피릿쇼 2025] 1차 얼리버드 티켓오픈 안내","contents":"2025-04-01(화) 09:00","link":"http://m.ticket.yes24.com/Notice/Detail.aspx?bid=15835&order=1","retrieved":1743384487330}]}