{"title":"예스24 티켓","url":"http://ticket.yes24.com/New/Notice/NoticeMain.aspx","favicon":"http://tkfile.yes24.com/img/icon.png","elements":[{"title":"뮤지컬 <명성황후> 30주년 기념 공연 - 광주 티켓오픈 안내","contents":"2025.03.26(수) 14:00","link":"http://ticket.yes24.com/New/Notice/NoticeMain.aspx#id=15812","retrieved":1742793537965},{"title":"2025 영동세계국악엑스포 티켓오픈 안내","contents":"2025.04.01(화) 09:00","link":"http://ticket.yes24.com/New/Notice/NoticeMain.aspx#id=15811","retrieved":1742785354762},{"title":"한지호 피아노 리사이틀 〈어린왕자〉 티켓오픈 안내입니다.","contents":"2025.03.25(화) 11:00","link":"http://ticket.yes24.com/New/Notice/NoticeMain.aspx#id=15810","retrieved":1742785354762},{"title":"단독판매[서울] 김희재 콘서트 ‘HEERE WE GO’ 티켓 오픈 안내","contents":"2025.03.27(목) 20:00","link":"http://ticket.yes24.com/New/Notice/NoticeMain.aspx#id=15809","retrieved":1742785354764},{"title":"모스크바 라 클라시크 발레단 월드투어〈백조의 호수〉- 부산 티켓오픈안내","contents":"2025.03.31(월) 14:00","link":"http://ticket.yes24.com/New/Notice/NoticeMain.aspx#id=15808","retrieved":1742785354764},{"title":"모스크바 라 클라시크 발레단 월드투어〈백조의 호수〉- 고양 티켓오픈안내","contents":"2025.03.31(월) 14:00","link":"http://ticket.yes24.com/New/Notice/NoticeMain.aspx#id=15807","retrieved":1742785354765},{"title":"2025 뮤지컬 <여신님이 보고 계셔> - 광주공연 티켓오픈 안내","contents":"2025.03.27(목) 14:00","link":"http://ticket.yes24.com/New/Notice/NoticeMain.aspx#id=15806","retrieved":1742548777802},{"title":"[부산] 연극 [얼씨구 왕국의 삼총사] 티켓오픈 안내","contents":"2025.03.28(금) 09:00","link":"http://ticket.yes24.com/New/Notice/NoticeMain.aspx#id=15805","retrieved":1742538470413},{"title":"[구로] 그리스 로마 신화 [신들의 왕 제우스] 티켓오픈 안내","contents":"2025.03.27(목) 10:00","link":"http://ticket.yes24.com/New/Notice/NoticeMain.aspx#id=15804","retrieved":1742779550533},{"title":"연극 [나생문] 티켓오픈 안내","contents":"2025.03.24(월) 11:00","link":"http://ticket.yes24.com/New/Notice/NoticeMain.aspx#id=15803","retrieved":1742538470416},{"title":"단독판매하성운 (HA SUNG WOON) 공식 팬클럽 HA:NEUL 4기 모집 안내","contents":"2025.03.31(월) 12:00","link":"http://ticket.yes24.com/New/Notice/NoticeMain.aspx#id=15802","retrieved":1742527958496},{"title":"음악극 [노베첸토] 2차 티켓 오픈 공지","contents":"2025.03.26(수) 15:00<a class=\"noti-btn-pop\" presaletit1=\"선예매\" presaletit2=\"\" presaletime1=\"2025.03.26(수) 11:00\" presaletime2=\"\"><img src=\"http://tkfile.yes24.com/imgNew/common/btn-notice1.png\" alt=\"\"></a>","link":"http://ticket.yes24.com/New/Notice/NoticeMain.aspx#id=15801","retrieved":1742525890390},{"title":"뮤지컬 [니진스키] 2차 티켓오픈 안내","contents":"2025.03.25(화) 15:00","link":"http://ticket.yes24.com/New/Notice/NoticeMain.aspx#id=15800","retrieved":1742447884942},{"title":"연극 [우리 노래방 가서… 얘기 좀 할까] 마지막 티켓 오픈 안내","contents":"2025.03.27(목) 14:00","link":"http://ticket.yes24.com/New/Notice/NoticeMain.aspx#id=15799","retrieved":1742447884942},{"title":"[부산] 2025 라이브가족뮤지컬 [프린세스공주] 티켓오픈 안내","contents":"2025.03.25(화) 10:00","link":"http://ticket.yes24.com/New/Notice/NoticeMain.aspx#id=15798","retrieved":1742459045850},{"title":"[대구] 어린이 서커스 마술쇼 티켓오픈 안내","contents":"2025.03.25(화) 10:00","link":"http://ticket.yes24.com/New/Notice/NoticeMain.aspx#id=15797","retrieved":1742439395584},{"title":"뮤지컬 [소란스러운 나의 서림에서] 2차 티켓오픈 안내","contents":"2025.03.27(목) 11:00","link":"http://ticket.yes24.com/New/Notice/NoticeMain.aspx#id=15796","retrieved":1742447884944},{"title":"뮤지컬 [이솝이야기] 2차 티켓오픈 안내","contents":"2025.03.25(화) 13:00","link":"http://ticket.yes24.com/New/Notice/NoticeMain.aspx#id=15795","retrieved":1742447884945},{"title":"[대전] 2025 윤종신 전국투어 콘서트 [그때] 티켓 오픈 안내","contents":"2025.03.25(화) 20:00","link":"http://ticket.yes24.com/New/Notice/NoticeMain.aspx#id=15794","retrieved":1742361478296},{"title":"단독판매2025 Road to BU-ROCK ~ SPYAIR ASIA TOUR 2025 -BUDDY- in Seoul 티켓 오픈 안내","contents":"2025.04.04(금) 19:00<a class=\"noti-btn-pop\" presaletit1=\"2회차 오픈\" presaletit2=\"\" presaletime1=\"2025.04.04(금) 19:30\" presaletime2=\"\"><img src=\"http://tkfile.yes24.com/imgNew/common/btn-notice1.png\" alt=\"\"></a>","link":"http://ticket.yes24.com/New/Notice/NoticeMain.aspx#id=15793","retrieved":1742353032256}]}